{
	"configurations" : 
	[
		{
			"directories" : 
			[
				{
					"build" : ".",
					"hasInstallRule" : true,
					"jsonFile" : "directory-.-572b1e74a9d08ea40a33.json",
					"minimumCMakeVersion" : 
					{
						"string" : "3.12"
					},
					"projectIndex" : 0,
					"source" : ".",
					"targetIndexes" : 
					[
						0,
						1,
						2,
						3,
						4,
						5,
						6,
						7
					]
				}
			],
			"name" : "",
			"projects" : 
			[
				{
					"directoryIndexes" : 
					[
						0
					],
					"name" : "my_robot",
					"targetIndexes" : 
					[
						0,
						1,
						2,
						3,
						4,
						5,
						6,
						7
					]
				}
			],
			"targets" : 
			[
				{
					"directoryIndex" : 0,
					"id" : "effort_translator::@6890427a1f51a3e7e1df",
					"jsonFile" : "target-effort_translator-060f7c48d3267c4a680b.json",
					"name" : "effort_translator",
					"projectIndex" : 0
				},
				{
					"directoryIndex" : 0,
					"id" : "gazebo_translator::@6890427a1f51a3e7e1df",
					"jsonFile" : "target-gazebo_translator-acc600c67792918c9843.json",
					"name" : "gazebo_translator",
					"projectIndex" : 0
				},
				{
					"directoryIndex" : 0,
					"id" : "hardware_translator::@6890427a1f51a3e7e1df",
					"jsonFile" : "target-hardware_translator-627971a4d56dbd81c0a0.json",
					"name" : "hardware_translator",
					"projectIndex" : 0
				},
				{
					"directoryIndex" : 0,
					"id" : "joystick_teleop::@6890427a1f51a3e7e1df",
					"jsonFile" : "target-joystick_teleop-e393147dd964ee093e85.json",
					"name" : "joystick_teleop",
					"projectIndex" : 0
				},
				{
					"directoryIndex" : 0,
					"id" : "listener::@6890427a1f51a3e7e1df",
					"jsonFile" : "target-listener-ed058bbd2ba445a93f21.json",
					"name" : "listener",
					"projectIndex" : 0
				},
				{
					"directoryIndex" : 0,
					"id" : "my_robot_uninstall::@6890427a1f51a3e7e1df",
					"jsonFile" : "target-my_robot_uninstall-4c79c36f3deb8ae9d868.json",
					"name" : "my_robot_uninstall",
					"projectIndex" : 0
				},
				{
					"directoryIndex" : 0,
					"id" : "talker::@6890427a1f51a3e7e1df",
					"jsonFile" : "target-talker-14abf4b6e19afb263af8.json",
					"name" : "talker",
					"projectIndex" : 0
				},
				{
					"directoryIndex" : 0,
					"id" : "uninstall::@6890427a1f51a3e7e1df",
					"jsonFile" : "target-uninstall-a5c08e197d58d33a9acd.json",
					"name" : "uninstall",
					"projectIndex" : 0
				}
			]
		}
	],
	"kind" : "codemodel",
	"paths" : 
	{
		"build" : "/home/dev/Documents/GitHub/Polar-Two/ros2_ws/build/my_robot",
		"source" : "/home/dev/Documents/GitHub/Polar-Two/ros2_ws/src/my_robot"
	},
	"version" : 
	{
		"major" : 2,
		"minor" : 3
	}
}
